automotive_fir_top.v
module automotive_fir_top (
    input  wire         clk,
    input  wire         rst_n,
    input  wire [15:0]  x_in,
    output wire [39:0]  y_out
);

    // 8-Tap Coefficients: Dolph-Chebyshev window (approx for 40dB sidelobe attenuation)
    // Quantized to 16-bit signed integers
    // h = [1024, 4096, 12288, 16384, 16384, 12288, 4096, 1024]
    localparam [15:0] H0 = 16'sd1024;
    localparam [15:0] H1 = 16'sd4096;
    localparam [15:0] H2 = 16'sd12288;
    localparam [15:0] H3 = 16'sd16384;
    localparam [15:0] H4 = 16'sd16384;
    localparam [15:0] H5 = 16'sd12288;
    localparam [15:0] H6 = 16'sd4096;
    localparam [15:0] H7 = 16'sd1024;

    // Stage 0: Input delay line (shift register)
    reg [15:0] x0, x1, x2, x3, x4, x5, x6, x7;

    always @(posedge clk or negedge rst_n) begin
        if (!rst_n) begin
            x0 <= 0; x1 <= 0; x2 <= 0; x3 <= 0;
            x4 <= 0; x5 <= 0; x6 <= 0; x7 <= 0;
        end else begin
            x0 <= x_in;
            x1 <= x0;
            x2 <= x1;
            x3 <= x2;
            x4 <= x3;
            x5 <= x4;
            x6 <= x5;
            x7 <= x6;
        end
    end

    // Stage 1: 16x16 Signed Multipliers
    reg signed [31:0] m0, m1, m2, m3, m4, m5, m6, m7;

    always @(posedge clk or negedge rst_n) begin
        if (!rst_n) begin
            m0 <= 0; m1 <= 0; m2 <= 0; m3 <= 0;
            m4 <= 0; m5 <= 0; m6 <= 0; m7 <= 0;
        end else begin
            m0 <= $signed(x0) * $signed(H0);
            m1 <= $signed(x1) * $signed(H1);
            m2 <= $signed(x2) * $signed(H2);
            m3 <= $signed(x3) * $signed(H3);
            m4 <= $signed(x4) * $signed(H4);
            m5 <= $signed(x5) * $signed(H5);
            m6 <= $signed(x6) * $signed(H6);
            m7 <= $signed(x7) * $signed(H7);
        end
    end

    // Stage 2: Adder Tree Level 2 (Registered to meet 500MHz timing)
    reg signed [33:0] sum_l2_0, sum_l2_1;

    always @(posedge clk or negedge rst_n) begin
        if (!rst_n) begin
            sum_l2_0 <= 0;
            sum_l2_1 <= 0;
        end else begin
            sum_l2_0 <= ($signed(m0) + $signed(m1)) + ($signed(m2) + $signed(m3));
            sum_l2_1 <= ($signed(m4) + $signed(m5)) + ($signed(m6) + $signed(m7));
        end
    end

    // Stage 3: Final Accumulator / Level 3 Adder
    reg signed [39:0] y_reg;

    always @(posedge clk or negedge rst_n) begin
        if (!rst_n) begin
            y_reg <= 0;
        end else begin
            y_reg <= $signed(sum_l2_0) + $signed(sum_l2_1);
        end
    end

    assign y_out = y_reg;

endmodule

automotive_fir_tb.v
`timescale 1ns/1ps
module automotive_fir_tb;
    reg clk;
    reg rst_n;
    reg [15:0] x_in;
    wire [39:0] y_out;

    automotive_fir_top dut (
        .clk(clk),
        .rst_n(rst_n),
        .x_in(x_in),
        .y_out(y_out)
    );

    always #1 clk = ~clk; // 500 MHz clock (2ns period)

    initial begin
        $dumpfile("automotive_fir.vcd");
        $dumpvars(0, automotive_fir_tb);
        clk = 0;
        rst_n = 0;
        x_in = 0;
        #5 rst_n = 1;

        @(posedge clk);
        x_in = 16'sd1000;
        @(posedge clk);
        x_in = 0;

        repeat(20) @(posedge clk);
        $display("PASS");
        $finish;
    end

    always @(posedge clk) begin
        if (rst_n)
            $display("t=%0t x_in=%d y_out=%d", $time, $signed(x_in), $signed(y_out));
    end
endmodule

automotive_fir.vcd
$date
	Mon Sep 21 16:22:23 2026
$end
$version
	Icarus Verilog
$end
$timescale
	1ps
$end
$scope module automotive_fir_tb $end
$var wire 40 ! y_out [39:0] $end
$var reg 1 " clk $end
$var reg 1 # rst_n $end
$var reg 16 $ x_in [15:0] $end
$scope module dut $end
$var wire 1 " clk $end
$var wire 1 # rst_n $end
$var wire 16 % x_in [15:0] $end
$var wire 40 & y_out [39:0] $end
$var parameter 16 ' H0 $end
$var parameter 16 ( H1 $end
$var parameter 16 ) H2 $end
$var parameter 16 * H3 $end
$var parameter 16 + H4 $end
$var parameter 16 , H5 $end
$var parameter 16 - H6 $end
$var parameter 16 . H7 $end
$var reg 32 / m0 [31:0] $end
$var reg 32 0 m1 [31:0] $end
$var reg 32 1 m2 [31:0] $end
$var reg 32 2 m3 [31:0] $end
$var reg 32 3 m4 [31:0] $end
$var reg 32 4 m5 [31:0] $end
$var reg 32 5 m6 [31:0] $end
$var reg 32 6 m7 [31:0] $end
$var reg 34 7 sum_l2_0 [33:0] $end
$var reg 34 8 sum_l2_1 [33:0] $end
$var reg 16 9 x0 [15:0] $end
$var reg 16 : x1 [15:0] $end
$var reg 16 ; x2 [15:0] $end
$var reg 16 < x3 [15:0] $end
$var reg 16 = x4 [15:0] $end
$var reg 16 > x5 [15:0] $end
$var reg 16 ? x6 [15:0] $end
$var reg 16 @ x7 [15:0] $end
$var reg 40 A y_reg [39:0] $end
$upscope $end
$upscope $end
$enddefinitions $end
$comment Show the parameter values. $end
$dumpall
b10000000000 .
b1000000000000 -
b11000000000000 ,
b100000000000000 +
b100000000000000 *
b11000000000000 )
b1000000000000 (
b10000000000 '
$end
#0
$dumpvars
b0 A
b0 @
b0 ?
b0 >
b0 =
b0 <
b0 ;
b0 :
b0 9
b0 8
b0 7
b0 6
b0 5
b0 4
b0 3
b0 2
b0 1
b0 0
b0 /
b0 &
b0 %
b0 $
0#
0"
b0 !
$end
#1000
1"
#2000
0"
#3000
1"
#4000
0"
#5000
b1111101000 9
b1111101000 $
b1111101000 %
1"
1#
#6000
0"
#7000
b1111101000 :
b0 9
b11111010000000000000 /
b0 $
b0 %
1"
#8000
0"
#9000
b11111010000000000000 7
b1111101000000000000000 0
b0 /
b1111101000 ;
b0 :
1"
#10000
0"
#11000
b1111101000 <
b0 ;
b101110111000000000000000 1
b0 0
b1111101000000000000000 7
b11111010000000000000 !
b11111010000000000000 &
b11111010000000000000 A
1"
#12000
0"
#13000
b1111101000000000000000 !
b1111101000000000000000 &
b1111101000000000000000 A
b101110111000000000000000 7
b111110100000000000000000 2
b0 1
b1111101000 =
b0 <
1"
#14000
0"
#15000
b1111101000 >
b0 =
b111110100000000000000000 3
b0 2
b111110100000000000000000 7
b101110111000000000000000 !
b101110111000000000000000 &
b101110111000000000000000 A
1"
#16000
0"
#17000
b111110100000000000000000 !
b111110100000000000000000 &
b111110100000000000000000 A
b111110100000000000000000 8
b0 7
b101110111000000000000000 4
b0 3
b1111101000 ?
b0 >
1"
#18000
0"
#19000
b1111101000 @
b0 ?
b1111101000000000000000 5
b0 4
b101110111000000000000000 8
1"
#20000
0"
#21000
b101110111000000000000000 !
b101110111000000000000000 &
b101110111000000000000000 A
b1111101000000000000000 8
b11111010000000000000 6
b0 5
b0 @
1"
#22000
0"
#23000
b0 6
b11111010000000000000 8
b1111101000000000000000 !
b1111101000000000000000 &
b1111101000000000000000 A
1"
#24000
0"
#25000
b11111010000000000000 !
b11111010000000000000 &
b11111010000000000000 A
b0 8
1"
#26000
0"
#27000
b0 !
b0 &
b0 A
1"
