simple_counter.v
module simple_counter(
    input wire clk,
    input wire rst_n,
    input wire load,
    input wire [3:0] d,
    output reg [3:0] q
);
    always @(posedge clk or negedge rst_n) begin
        if (!rst_n)
            q <= 4'b0000;
        else if (load)
            q <= d;
        else
            q <= q + 1'b1;
    end
endmodule

tb_counter.v
module tb_counter;
    reg clk;
    reg rst_n;
    reg load;
    reg [3:0] d;
    wire [3:0] q;

    simple_counter u0 (
        .clk(clk),
        .rst_n(rst_n),
        .load(load),
        .d(d),
        .q(q)
    );

    initial begin
        $dumpfile("test.vcd");
        $dumpvars(0, tb_counter);
        clk = 0;
        rst_n = 0;
        load = 0;
        d = 4'h0;
        #15 rst_n = 1;
        #20 load = 1; d = 4'h5;
        #10 load = 0;
        #100;
        $display("PASS");
        $finish;
    end

    always #5 clk = ~clk;
endmodule

test.vcd
$date
	Tue Sep 22 00:17:00 2026
$end
$version
	Icarus Verilog
$end
$timescale
	1s
$end
$scope module tb_counter $end
$var wire 4 ! q [3:0] $end
$var reg 1 " clk $end
$var reg 4 # d [3:0] $end
$var reg 1 $ load $end
$var reg 1 % rst_n $end
$scope module u0 $end
$var wire 1 " clk $end
$var wire 4 & d [3:0] $end
$var wire 1 $ load $end
$var wire 1 % rst_n $end
$var reg 4 ' q [3:0] $end
$upscope $end
$upscope $end
$enddefinitions $end
$comment Show the parameter values. $end
$dumpall
$end
#0
$dumpvars
b0 '
b0 &
0%
0$
b0 #
0"
b0 !
$end
#5
1"
#10
0"
#15
b1 !
b1 '
1"
1%
#20
0"
#25
b10 !
b10 '
1"
#30
0"
#35
b101 !
b101 '
1"
b101 #
b101 &
1$
#40
0"
#45
b110 !
b110 '
1"
0$
#50
0"
#55
b111 !
b111 '
1"
#60
0"
#65
b1000 !
b1000 '
1"
#70
0"
#75
b1001 !
b1001 '
1"
#80
0"
#85
b1010 !
b1010 '
1"
#90
0"
#95
b1011 !
b1011 '
1"
#100
0"
#105
b1100 !
b1100 '
1"
#110
0"
#115
b1101 !
b1101 '
1"
#120
0"
#125
b1110 !
b1110 '
1"
#130
0"
#135
b1111 !
b1111 '
1"
#140
0"
#145
b0 !
b0 '
1"
